django_keyvaluestore-0.3.dist-info/DESCRIPTION.rst
django_keyvaluestore-0.3.dist-info/METADATA
django_keyvaluestore-0.3.dist-info/RECORD
django_keyvaluestore-0.3.dist-info/WHEEL
django_keyvaluestore-0.3.dist-info/metadata.json
django_keyvaluestore-0.3.dist-info/top_level.txt
keyvaluestore/__init__.py
keyvaluestore/admin.py
keyvaluestore/managers.py
keyvaluestore/models.py
keyvaluestore/utils.py
keyvaluestore/migrations/0001_initial.py
keyvaluestore/migrations/__init__.py
