Metadata-Version: 2.0
Name: django-keyvaluestore
Version: 0.3
Summary: A Key-Value store for Django
Home-page: https://github.com/vikingco/django-keyvaluestore
Author: Unleashed NV
Author-email: operations@unleashed.be
License: BSD
Platform: UNKNOWN
Classifier: Intended Audience :: Developers
Classifier: Programming Language :: Python
Classifier: Operating System :: OS Independent
Classifier: Environment :: Web Environment
Classifier: Framework :: Django
